{"version": 0.6, "generator": "Overpass API 0.7.62.4 2390de5a", "osm3s": {"timestamp_osm_base": "2025-01-12T13:56:56Z", "copyright": "The data included in this document is from www.openstreetmap.org. The data is made available under ODbL."}, "elements": [{"type": "node", "id": 33193742, "lat": 37.5340304, "lon": -3.9809097}, {"type": "node", "id": 33193743, "lat": 37.5344964, "lon": -3.9813582}, {"type": "node", "id": 33193744, "lat": 37.5351478, "lon": -3.9826209}, {"type": "node", "id": 33193745, "lat": 37.5353184, "lon": -3.9836977}, {"type": "node", "id": 33193746, "lat": 37.5352664, "lon": -3.9850224}, {"type": "node", "id": 33193747, "lat": 37.5352617, "lon": -3.9862171}, {"type": "node", "id": 33193748, "lat": 37.5355216, "lon": -3.9873693}, {"type": "node", "id": 33193749, "lat": 37.5363421, "lon": -3.988626}, {"type": "node", "id": 33193750, "lat": 37.5369267, "lon": -3.9892971}, {"type": "node", "id": 33193752, "lat": 37.5375264, "lon": -3.9904028}, {"type": "node", "id": 33193753, "lat": 37.5376552, "lon": -3.9907625}, {"type": "node", "id": 33193754, "lat": 37.5383285, "lon": -3.9934872}, {"type": "node", "id": 33193755, "lat": 37.5388478, "lon": -3.9947248}, {"type": "node", "id": 33193756, "lat": 37.5402992, "lon": -3.9972142}, {"type": "node", "id": 33193757, "lat": 37.5404666, "lon": -3.9976585}, {"type": "node", "id": 33193758, "lat": 37.5406191, "lon": -3.9984431}, {"type": "node", "id": 33193759, "lat": 37.5405629, "lon": -3.9993166}, {"type": "node", "id": 33193760, "lat": 37.5401053, "lon": -4.0019745}, {"type": "node", "id": 33193761, "lat": 37.5399911, "lon": -4.0028028}, {"type": "node", "id": 33193762, "lat": 37.540015, "lon": -4.0042215}, {"type": "node", "id": 33193763, "lat": 37.540361, "lon": -4.0056686}, {"type": "node", "id": 33193764, "lat": 37.5409587, "lon": -4.006864}, {"type": "node", "id": 33193765, "lat": 37.5422132, "lon": -4.0085045}, {"type": "node", "id": 33193766, "lat": 37.5426673, "lon": -4.0093199}, {"type": "node", "id": 33193767, "lat": 37.5432492, "lon": -4.0106751}, {"type": "node", "id": 33193768, "lat": 37.5434197, "lon": -4.011247}, {"type": "node", "id": 33193769, "lat": 37.5432412, "lon": -4.0126484}, {"type": "node", "id": 33193770, "lat": 37.542975, "lon": -4.0138051}, {"type": "node", "id": 33193771, "lat": 37.542945, "lon": -4.0143293}, {"type": "node", "id": 33193773, "lat": 37.5430736, "lon": -4.0159728}, {"type": "node", "id": 33193774, "lat": 37.5437626, "lon": -4.0240704}, {"type": "node", "id": 33193775, "lat": 37.5448911, "lon": -4.0343592}, {"type": "node", "id": 33193776, "lat": 37.5449855, "lon": -4.0349569}, {"type": "node", "id": 33193777, "lat": 37.5454358, "lon": -4.0359683}, {"type": "node", "id": 33193778, "lat": 37.5461994, "lon": -4.0374224}, {"type": "node", "id": 33193779, "lat": 37.5470452, "lon": -4.0391089}, {"type": "node", "id": 33193780, "lat": 37.5477583, "lon": -4.0407673}, {"type": "node", "id": 877550507, "lat": 37.5330122, "lon": -3.946732}, {"type": "node", "id": 1041687592, "lat": 37.5831462, "lon": -4.0601}, {"type": "node", "id": 1041687619, "lat": 37.5775959, "lon": -4.0565691}, {"type": "node", "id": 1041687630, "lat": 37.5855035, "lon": -4.0628891}, {"type": "node", "id": 1041687632, "lat": 37.5819752, "lon": -4.059407}, {"type": "node", "id": 1041687637, "lat": 37.5768611, "lon": -4.0555235}, {"type": "node", "id": 1041687657, "lat": 37.5806967, "lon": -4.0584809}, {"type": "node", "id": 1041687682, "lat": 37.579914, "lon": -4.0580687}, {"type": "node", "id": 1041687706, "lat": 37.5841201, "lon": -4.0609723}, {"type": "node", "id": 1041687768, "lat": 37.5845682, "lon": -4.0616952}, {"type": "node", "id": 1041687785, "lat": 37.5788685, "lon": -4.0576624}, {"type": "node", "id": 1041687849, "lat": 37.583433, "lon": -4.0603211}, {"type": "node", "id": 1041687907, "lat": 37.57805, "lon": -4.0568917}, {"type": "node", "id": 1041687962, "lat": 37.5824651, "lon": -4.0597057}, {"type": "node", "id": 1041688010, "lat": 37.5771538, "lon": -4.0560194}, {"type": "node", "id": 1041688085, "lat": 37.577339, "lon": -4.0562883}, {"type": "node", "id": 1041688154, "lat": 37.5811567, "lon": -4.0588035}, {"type": "node", "id": 1041688362, "lat": 37.580165, "lon": -4.0581702}, {"type": "node", "id": 1041688479, "lat": 37.579454, "lon": -4.0579133}, {"type": "node", "id": 1041688543, "lat": 37.5849359, "lon": -4.0622319}, {"type": "node", "id": 1041688588, "lat": 37.5838811, "lon": -4.0607273}, {"type": "node", "id": 1041688641, "lat": 37.5786594, "lon": -4.057513}, {"type": "node", "id": 1207222342, "lat": 37.52784, "lon": -4.0426558}, {"type": "node", "id": 1207222345, "lat": 37.5477633, "lon": -3.9669629}, {"type": "node", "id": 1207222363, "lat": 37.5131373, "lon": -4.0629934}, {"type": "node", "id": 1207222364, "lat": 37.5294692, "lon": -4.0358421}, {"type": "node", "id": 1207222371, "lat": 37.5425007, "lon": -3.9600363}, {"type": "node", "id": 1207222389, "lat": 37.4894457, "lon": -4.0505202}, {"type": "node", "id": 1207222391, "lat": 37.5375956, "lon": -4.0376013}, {"type": "node", "id": 1207222393, "lat": 37.5324839, "lon": -4.032872}, {"type": "node", "id": 1207222397, "lat": 37.543344, "lon": -3.9924442}, {"type": "node", "id": 1207222410, "lat": 37.4968546, "lon": -4.0529788}, {"type": "node", "id": 1207222412, "lat": 37.5441926, "lon": -4.0382278}, {"type": "node", "id": 1207222413, "lat": 37.5249159, "lon": -4.0485719}, {"type": "node", "id": 1207222414, "lat": 37.5456231, "lon": -3.9826938}, {"type": "node", "id": 1207222427, "lat": 37.4653896, "lon": -4.0248983}, {"type": "node", "id": 1207222429, "lat": 37.5254175, "lon": -4.0442864}, {"type": "node", "id": 1207222432, "lat": 37.5476971, "lon": -3.9735594}, {"type": "node", "id": 1207222437, "lat": 37.4718487, "lon": -4.0413735}, {"type": "node", "id": 1207222443, "lat": 37.5139478, "lon": -4.0608824}, {"type": "node", "id": 1207222454, "lat": 37.4757215, "lon": -4.0485306}, {"type": "node", "id": 1207222465, "lat": 37.5191821, "lon": -4.0587775}, {"type": "node", "id": 1207222466, "lat": 37.5416533, "lon": -3.9924346}, {"type": "node", "id": 1207222469, "lat": 37.5348325, "lon": -3.9511658}, {"type": "node", "id": 1207222482, "lat": 37.5225365, "lon": -4.054482}, {"type": "node", "id": 1207222494, "lat": 37.4625826, "lon": -4.0174511}, {"type": "node", "id": 1207222498, "lat": 37.507242, "lon": -4.0604969}, {"type": "node", "id": 1207222524, "lat": 37.5113175, "lon": -4.0645936}, {"type": "node", "id": 1207222527, "lat": 37.5285041, "lon": -4.0399629}, {"type": "node", "id": 1207222530, "lat": 37.5454298, "lon": -3.9648584}, {"type": "node", "id": 1207222545, "lat": 37.4807606, "lon": -4.0494223}, {"type": "node", "id": 1207222547, "lat": 37.5309312, "lon": -4.0369868}, {"type": "node", "id": 1207222556, "lat": 37.5390861, "lon": -3.9578555}, {"type": "node", "id": 1207222564, "lat": 37.4923638, "lon": -4.0512822}, {"type": "node", "id": 1207222571, "lat": 37.5410733, "lon": -4.0400171}, {"type": "node", "id": 1207222572, "lat": 37.5234348, "lon": -4.0524035}, {"type": "node", "id": 1207222574, "lat": 37.5448986, "lon": -3.9886702}, {"type": "node", "id": 1207222582, "lat": 37.5026727, "lon": -4.055323}, {"type": "node", "id": 1207222584, "lat": 37.5461971, "lon": -4.0385888}, {"type": "node", "id": 1207222593, "lat": 37.526292, "lon": -4.0462766}, {"type": "node", "id": 1207222596, "lat": 37.5475172, "lon": -3.9783449}, {"type": "node", "id": 1207222600, "lat": 37.4696777, "lon": -4.032041}, {"type": "node", "id": 1207222604, "lat": 37.5268701, "lon": -4.041469}, {"type": "node", "id": 1207222615, "lat": 37.4738951, "lon": -4.0461028}, {"type": "node", "id": 1207222619, "lat": 37.5158038, "lon": -4.0618379}, {"type": "node", "id": 1207222621, "lat": 37.5408164, "lon": -3.9941022}, {"type": "node", "id": 1207222638, "lat": 37.5209692, "lon": -4.0567532}, {"type": "node", "id": 1207222641, "lat": 37.5422924, "lon": -3.9903674}, {"type": "node", "id": 1207222653, "lat": 37.5331891, "lon": -3.9470981}, {"type": "node", "id": 1207222658, "lat": 37.5050065, "lon": -4.0588818}, {"type": "node", "id": 1207222674, "lat": 37.4644791, "lon": -4.0220789}, {"type": "node", "id": 1207222679, "lat": 37.5088401, "lon": -4.0613933}, {"type": "node", "id": 1207222691, "lat": 37.5483811, "lon": -3.9678096}, {"type": "node", "id": 1207222703, "lat": 37.5132176, "lon": -4.063379}, {"type": "node", "id": 1207222705, "lat": 37.5299135, "lon": -4.0372217}, {"type": "node", "id": 1207222707, "lat": 37.5430975, "lon": -3.9610541}, {"type": "node", "id": 1207222727, "lat": 37.4884777, "lon": -4.0503546}, {"type": "node", "id": 1207222728, "lat": 37.5371179, "lon": -4.037288}, {"type": "node", "id": 1207222729, "lat": 37.5323883, "lon": -4.0326551}, {"type": "node", "id": 1207222732, "lat": 37.5368963, "lon": -3.9551902}, {"type": "node", "id": 1207222748, "lat": 37.4960684, "lon": -4.0525585}, {"type": "node", "id": 1207222750, "lat": 37.5432946, "lon": -4.0390652}, {"type": "node", "id": 1207222759, "lat": 37.5252456, "lon": -4.0496563}, {"type": "node", "id": 1207222760, "lat": 37.5456855, "lon": -3.9841582}, {"type": "node", "id": 1207222763, "lat": 37.4652786, "lon": -4.0245995}, {"type": "node", "id": 1207222764, "lat": 37.5255622, "lon": -4.0445815}, {"type": "node", "id": 1207222766, "lat": 37.5476677, "lon": -3.9738421}, {"type": "node", "id": 1207222779, "lat": 37.4717148, "lon": -4.0410422}, {"type": "node", "id": 1207222785, "lat": 37.5138828, "lon": -4.061056}, {"type": "node", "id": 1207222797, "lat": 37.4754298, "lon": -4.0482354}, {"type": "node", "id": 1207222800, "lat": 37.5191009, "lon": -4.059392}, {"type": "node", "id": 1207222801, "lat": 37.5414867, "lon": -3.9927097}, {"type": "node", "id": 1207222806, "lat": 37.5350885, "lon": -3.9515707}, {"type": "node", "id": 1207222813, "lat": 37.5221877, "lon": -4.0551507}, {"type": "node", "id": 1207222827, "lat": 37.4618247, "lon": -4.0164121}, {"type": "node", "id": 1207222831, "lat": 37.507005, "lon": -4.0608053}, {"type": "node", "id": 1207222861, "lat": 37.5111608, "lon": -4.0643767}, {"type": "node", "id": 1207222864, "lat": 37.5282461, "lon": -4.0409087}, {"type": "node", "id": 1207222866, "lat": 37.5459865, "lon": -3.9651491}, {"type": "node", "id": 1207222887, "lat": 37.4796658, "lon": -4.0496572}, {"type": "node", "id": 1207222888, "lat": 37.5304916, "lon": -4.0368121}, {"type": "node", "id": 1207222890, "lat": 37.539388, "lon": -3.9580193}, {"type": "node", "id": 1207222918, "lat": 37.4919385, "lon": -4.051101}, {"type": "node", "id": 1207222921, "lat": 37.5407294, "lon": -4.0395592}, {"type": "node", "id": 1207222923, "lat": 37.5343471, "lon": -4.0356915}, {"type": "node", "id": 1207222925, "lat": 37.5448763, "lon": -3.9889384}, {"type": "node", "id": 1207222938, "lat": 37.5016969, "lon": -4.0550223}, {"type": "node", "id": 1207222941, "lat": 37.5461261, "lon": -4.038234}, {"type": "node", "id": 1207222943, "lat": 37.5262299, "lon": -4.046614}, {"type": "node", "id": 1207222946, "lat": 37.5476484, "lon": -3.9791464}, {"type": "node", "id": 1207222950, "lat": 37.4693335, "lon": -4.0317518}, {"type": "node", "id": 1207222959, "lat": 37.5266694, "lon": -4.0415594}, {"type": "node", "id": 1207222961, "lat": 37.5473328, "lon": -3.9710324}, {"type": "node", "id": 1207222965, "lat": 37.4737134, "lon": -4.0455244}, {"type": "node", "id": 1207222968, "lat": 37.5153976, "lon": -4.0618319}, {"type": "node", "id": 1207222970, "lat": 37.540659, "lon": -3.994142}, {"type": "node", "id": 1207222993, "lat": 37.5208928, "lon": -4.0570183}, {"type": "node", "id": 1207222999, "lat": 37.5422163, "lon": -3.9904393}, {"type": "node", "id": 1207223001, "lat": 37.5333649, "lon": -3.9478548}, {"type": "node", "id": 1207223008, "lat": 37.5046548, "lon": -4.0582842}, {"type": "node", "id": 1207223033, "lat": 37.4643529, "lon": -4.0216595}, {"type": "node", "id": 1207223037, "lat": 37.5084655, "lon": -4.0610608}, {"type": "node", "id": 1207223048, "lat": 37.5484052, "lon": -3.9682723}, {"type": "node", "id": 1207223071, "lat": 37.5133131, "lon": -4.0638128}, {"type": "node", "id": 1207223077, "lat": 37.5299135, "lon": -4.0376796}, {"type": "node", "id": 1207223080, "lat": 37.5434337, "lon": -3.9622076}, {"type": "node", "id": 1207223095, "lat": 37.4870376, "lon": -4.0498199}, {"type": "node", "id": 1207223098, "lat": 37.5364491, "lon": -4.0366434}, {"type": "node", "id": 1207223101, "lat": 37.5322593, "lon": -4.0326551}, {"type": "node", "id": 1207223103, "lat": 37.5375116, "lon": -3.9557975}, {"type": "node", "id": 1207223116, "lat": 37.4952853, "lon": -4.0520958}, {"type": "node", "id": 1207223118, "lat": 37.5426927, "lon": -4.0398243}, {"type": "node", "id": 1207223119, "lat": 37.5251501, "lon": -4.0500479}, {"type": "node", "id": 1207223120, "lat": 37.5455397, "lon": -3.9847079}, {"type": "node", "id": 1207223127, "lat": 37.4650453, "lon": -4.0242284}, {"type": "node", "id": 1207223145, "lat": 37.5256709, "lon": -4.0446259}, {"type": "node", "id": 1207223151, "lat": 37.5473252, "lon": -3.9743804}, {"type": "node", "id": 1207223155, "lat": 37.4710789, "lon": -4.0389516}, {"type": "node", "id": 1207223157, "lat": 37.5277445, "lon": -4.0428426}, {"type": "node", "id": 1207223177, "lat": 37.4752816, "lon": -4.0478499}, {"type": "node", "id": 1207223191, "lat": 37.5187951, "lon": -4.0598438}, {"type": "node", "id": 1207223193, "lat": 37.5416026, "lon": -3.9929753}, {"type": "node", "id": 1207223197, "lat": 37.5353599, "lon": -3.9527226}, {"type": "node", "id": 1207223209, "lat": 37.5222593, "lon": -4.0559219}, {"type": "node", "id": 1207223216, "lat": 37.5430599, "lon": -3.992221}, {"type": "node", "id": 1207223244, "lat": 37.5068406, "lon": -4.0608391}, {"type": "node", "id": 1207223266, "lat": 37.510962, "lon": -4.0642176}, {"type": "node", "id": 1207223272, "lat": 37.5279929, "lon": -4.0411557}, {"type": "node", "id": 1207223276, "lat": 37.5461788, "lon": -3.9654271}, {"type": "node", "id": 1207223299, "lat": 37.4791208, "lon": -4.0496693}, {"type": "node", "id": 1207223300, "lat": 37.5301047, "lon": -4.0364265}, {"type": "node", "id": 1207223304, "lat": 37.5398313, "lon": -3.9582314}, {"type": "node", "id": 1207223315, "lat": 37.4917733, "lon": -4.0509854}, {"type": "node", "id": 1207223326, "lat": 37.540266, "lon": -4.039246}, {"type": "node", "id": 1207223330, "lat": 37.5327371, "lon": -4.0352879}, {"type": "node", "id": 1207223332, "lat": 37.5443888, "lon": -3.9906499}, {"type": "node", "id": 1207223342, "lat": 37.499366, "lon": -4.0540159}, {"type": "node", "id": 1207223343, "lat": 37.5459271, "lon": -4.0380054}, {"type": "node", "id": 1207223345, "lat": 37.526077, "lon": -4.0469031}, {"type": "node", "id": 1207223348, "lat": 37.5476506, "lon": -3.9792643}, {"type": "node", "id": 1207223352, "lat": 37.4687635, "lon": -4.0310192}, {"type": "node", "id": 1207223355, "lat": 37.5262299, "lon": -4.0426438}, {"type": "node", "id": 1207223370, "lat": 37.5471519, "lon": -3.9715191}, {"type": "node", "id": 1207223384, "lat": 37.4734839, "lon": -4.0433255}, {"type": "node", "id": 1207223390, "lat": 37.5151587, "lon": -4.0616994}, {"type": "node", "id": 1207223391, "lat": 37.5402027, "lon": -3.9946082}, {"type": "node", "id": 1207223407, "lat": 37.5208641, "lon": -4.0573677}, {"type": "node", "id": 1207223412, "lat": 37.5421803, "lon": -3.9907759}, {"type": "node", "id": 1207223417, "lat": 37.53364, "lon": -3.9484283}, {"type": "node", "id": 1207223436, "lat": 37.5232341, "lon": -4.0526566}, {"type": "node", "id": 1207223447, "lat": 37.4637369, "lon": -4.0206571}, {"type": "node", "id": 1207223451, "lat": 37.5080946, "lon": -4.060386}, {"type": "node", "id": 1207223462, "lat": 37.5481531, "lon": -3.9686948}, {"type": "node", "id": 1207223487, "lat": 37.5132023, "lon": -4.0641983}, {"type": "node", "id": 1207223490, "lat": 37.529689, "lon": -4.0381073}, {"type": "node", "id": 1207223500, "lat": 37.5433688, "lon": -3.9628068}, {"type": "node", "id": 1207223508, "lat": 37.4863874, "lon": -4.0496331}, {"type": "node", "id": 1207223522, "lat": 37.5361147, "lon": -4.0364747}, {"type": "node", "id": 1207223523, "lat": 37.5321351, "lon": -4.0328359}, {"type": "node", "id": 1207223527, "lat": 37.5377218, "lon": -3.9562987}, {"type": "node", "id": 1207223540, "lat": 37.4944379, "lon": -4.0519686}, {"type": "node", "id": 1207223542, "lat": 37.5423774, "lon": -4.0405232}, {"type": "node", "id": 1207223544, "lat": 37.5249637, "lon": -4.0502889}, {"type": "node", "id": 1207223546, "lat": 37.5447352, "lon": -3.9858177}, {"type": "node", "id": 1207223554, "lat": 37.464678, "lon": -4.0237464}, {"type": "node", "id": 1207223564, "lat": 37.5260818, "lon": -4.0447584}, {"type": "node", "id": 1207223567, "lat": 37.5471609, "lon": -3.974986}, {"type": "node", "id": 1207223574, "lat": 37.4710502, "lon": -4.0383733}, {"type": "node", "id": 1207223579, "lat": 37.5276202, "lon": -4.0428908}, {"type": "node", "id": 1207223590, "lat": 37.4750091, "lon": -4.0470426}, {"type": "node", "id": 1207223611, "lat": 37.5182169, "lon": -4.0601149}, {"type": "node", "id": 1207223614, "lat": 37.5417609, "lon": -3.9932982}, {"type": "node", "id": 1207223616, "lat": 37.5356848, "lon": -3.9534696}, {"type": "node", "id": 1207223623, "lat": 37.5221303, "lon": -4.0562291}, {"type": "node", "id": 1207223645, "lat": 37.5428523, "lon": -3.9917723}, {"type": "node", "id": 1207223658, "lat": 37.5064085, "lon": -4.0605354}, {"type": "node", "id": 1207223699, "lat": 37.5105567, "lon": -4.0634947}, {"type": "node", "id": 1207223706, "lat": 37.5277301, "lon": -4.0414449}, {"type": "node", "id": 1207223712, "lat": 37.5466552, "lon": -3.9656263}, {"type": "node", "id": 1207223735, "lat": 37.5139401, "lon": -4.0615138}, {"type": "node", "id": 1207223737, "lat": 37.5297511, "lon": -4.0355288}, {"type": "node", "id": 1207223744, "lat": 37.540095, "lon": -3.9585061}, {"type": "node", "id": 1207223767, "lat": 37.4915745, "lon": -4.0506692}, {"type": "node", "id": 1207223769, "lat": 37.5396976, "lon": -4.0389387}, {"type": "node", "id": 1207223770, "lat": 37.5324982, "lon": -4.035077}, {"type": "node", "id": 1207223773, "lat": 37.5442967, "lon": -3.9912238}, {"type": "node", "id": 1207223784, "lat": 37.4980599, "lon": -4.0537576}, {"type": "node", "id": 1207223786, "lat": 37.5454603, "lon": -4.0380267}, {"type": "node", "id": 1207223788, "lat": 37.5258572, "lon": -4.0476321}, {"type": "node", "id": 1207223790, "lat": 37.5468045, "lon": -3.9805451}, {"type": "node", "id": 1207223799, "lat": 37.4657415, "lon": -4.0269081}, {"type": "node", "id": 1207223800, "lat": 37.5261534, "lon": -4.04318}, {"type": "node", "id": 1207223804, "lat": 37.5471723, "lon": -3.9719914}, {"type": "node", "id": 1207223819, "lat": 37.4732639, "lon": -4.0428495}, {"type": "node", "id": 1207223821, "lat": 37.5148767, "lon": -4.0614608}, {"type": "node", "id": 1207223823, "lat": 37.5400797, "lon": -3.9955088}, {"type": "node", "id": 1207223850, "lat": 37.5207064, "lon": -4.0575906}, {"type": "node", "id": 1207223853, "lat": 37.5423501, "lon": -3.9912875}, {"type": "node", "id": 1207223854, "lat": 37.5340108, "lon": -3.9491175}, {"type": "node", "id": 1207223862, "lat": 37.523, "lon": -4.0528252}, {"type": "node", "id": 1207223878, "lat": 37.4636222, "lon": -4.0203341}, {"type": "node", "id": 1207223883, "lat": 37.5077811, "lon": -4.0598944}, {"type": "node", "id": 1207223886, "lat": 37.5468684, "lon": -4.0387508}, {"type": "node", "id": 1207223903, "lat": 37.5481085, "lon": -3.9688186}, {"type": "node", "id": 1207223917, "lat": 37.5127665, "lon": -4.0647381}, {"type": "node", "id": 1207223926, "lat": 37.5380638, "lon": -3.9925628}, {"type": "node", "id": 1207223927, "lat": 37.5294023, "lon": -4.0383061}, {"type": "node", "id": 1207223930, "lat": 37.5435662, "lon": -3.9633401}, {"type": "node", "id": 1207223946, "lat": 37.4834952, "lon": -4.0491391}, {"type": "node", "id": 1207223947, "lat": 37.5316144, "lon": -4.0348902}, {"type": "node", "id": 1207223949, "lat": 37.5380695, "lon": -3.9565542}, {"type": "node", "id": 1207223961, "lat": 37.4939607, "lon": -4.0518452}, {"type": "node", "id": 1207223962, "lat": 37.5422539, "lon": -4.0407464}, {"type": "node", "id": 1207223963, "lat": 37.5243187, "lon": -4.0507287}, {"type": "node", "id": 1207223965, "lat": 37.5444168, "lon": -3.9866957}, {"type": "node", "id": 1207223972, "lat": 37.5039115, "lon": -4.0566571}, {"type": "node", "id": 1207223973, "lat": 37.5261917, "lon": -4.0449271}, {"type": "node", "id": 1207223974, "lat": 37.5471277, "lon": -3.9763291}, {"type": "node", "id": 1207223979, "lat": 37.4714375, "lon": -4.0339031}, {"type": "node", "id": 1207223983, "lat": 37.5275103, "lon": -4.0427824}, {"type": "node", "id": 1207223999, "lat": 37.4747079, "lon": -4.0467173}, {"type": "node", "id": 1207224005, "lat": 37.5173998, "lon": -4.0609102}, {"type": "node", "id": 1207224013, "lat": 37.5417622, "lon": -3.9937054}, {"type": "node", "id": 1207224016, "lat": 37.5360325, "lon": -3.9539178}, {"type": "node", "id": 1207224030, "lat": 37.5218484, "lon": -4.0563436}, {"type": "node", "id": 1207224035, "lat": 37.5427179, "lon": -3.9911715}, {"type": "node", "id": 1207224052, "lat": 37.5059918, "lon": -4.0599619}, {"type": "node", "id": 1207224085, "lat": 37.5102623, "lon": -4.0630947}, {"type": "node", "id": 1207224088, "lat": 37.5275916, "lon": -4.0422161}, {"type": "node", "id": 1207224102, "lat": 37.5471685, "lon": -3.965938}, {"type": "node", "id": 1207224106, "lat": 37.5137413, "lon": -4.0623958}, {"type": "node", "id": 1207224108, "lat": 37.52956, "lon": -4.0353782}, {"type": "node", "id": 1207224110, "lat": 37.5407065, "lon": -3.9586314}, {"type": "node", "id": 1207224122, "lat": 37.4911584, "lon": -4.050808}, {"type": "node", "id": 1207224124, "lat": 37.5390192, "lon": -4.0382338}, {"type": "node", "id": 1207224126, "lat": 37.5323644, "lon": -4.0347456}, {"type": "node", "id": 1207224131, "lat": 37.5439248, "lon": -3.9921181}, {"type": "node", "id": 1207224147, "lat": 37.4976285, "lon": -4.0536072}, {"type": "node", "id": 1207224149, "lat": 37.5449903, "lon": -4.0380832}, {"type": "node", "id": 1207224151, "lat": 37.5252743, "lon": -4.0478731}, {"type": "node", "id": 1207224154, "lat": 37.5464049, "lon": -3.9807808}, {"type": "node", "id": 1207224160, "lat": 37.4655693, "lon": -4.026431}, {"type": "node", "id": 1207224161, "lat": 37.525948, "lon": -4.0434631}, {"type": "node", "id": 1207224164, "lat": 37.5473519, "lon": -3.9726067}, {"type": "node", "id": 1207224174, "lat": 37.4729627, "lon": -4.0425061}, {"type": "node", "id": 1207224177, "lat": 37.514525, "lon": -4.0611234}, {"type": "node", "id": 1207224178, "lat": 37.5399418, "lon": -3.9959791}, {"type": "node", "id": 1207224183, "lat": 37.4776196, "lon": -4.0495367}, {"type": "node", "id": 1207224186, "lat": 37.5201091, "lon": -4.057934}, {"type": "node", "id": 1207224187, "lat": 37.5422765, "lon": -3.9920937}, {"type": "node", "id": 1207224189, "lat": 37.5343242, "lon": -3.9500766}, {"type": "node", "id": 1207224200, "lat": 37.5228948, "lon": -4.0533253}, {"type": "node", "id": 1207224209, "lat": 37.4629833, "lon": -4.018175}, {"type": "node", "id": 1207224212, "lat": 37.5075402, "lon": -4.0598462}, {"type": "node", "id": 1207224213, "lat": 37.5466465, "lon": -4.0388818}, {"type": "node", "id": 1207224220, "lat": 37.5480639, "lon": -3.9694852}, {"type": "node", "id": 1207224240, "lat": 37.5121051, "lon": -4.0649984}, {"type": "node", "id": 1207224245, "lat": 37.5288911, "lon": -4.0385471}, {"type": "node", "id": 1207224247, "lat": 37.5437484, "lon": -3.9635426}, {"type": "node", "id": 1207224258, "lat": 37.4828833, "lon": -4.049115}, {"type": "node", "id": 1207224259, "lat": 37.5313946, "lon": -4.0367398}, {"type": "node", "id": 1207224262, "lat": 37.5383371, "lon": -3.9569638}, {"type": "node", "id": 1207224271, "lat": 37.4936395, "lon": -4.0517951}, {"type": "node", "id": 1207224274, "lat": 37.5235255, "lon": -4.0516203}, {"type": "node", "id": 1207224275, "lat": 37.5444095, "lon": -3.9871697}, {"type": "node", "id": 1207224282, "lat": 37.5034068, "lon": -4.0559631}, {"type": "node", "id": 1207224283, "lat": 37.5262299, "lon": -4.0452464}, {"type": "node", "id": 1207224284, "lat": 37.5472602, "lon": -3.9768978}, {"type": "node", "id": 1207224287, "lat": 37.4711386, "lon": -4.0330891}, {"type": "node", "id": 1207224291, "lat": 37.5271855, "lon": -4.0421799}, {"type": "node", "id": 1207224300, "lat": 37.4744832, "lon": -4.0465787}, {"type": "node", "id": 1207224308, "lat": 37.5171513, "lon": -4.0615126}, {"type": "node", "id": 1207224309, "lat": 37.5415934, "lon": -3.9940019}, {"type": "node", "id": 1207224310, "lat": 37.5365638, "lon": -3.954448}, {"type": "node", "id": 1207224320, "lat": 37.5214327, "lon": -4.0563134}, {"type": "node", "id": 1207224323, "lat": 37.5426551, "lon": -3.990608}, {"type": "node", "id": 1207224329, "lat": 37.505551, "lon": -4.0597841}, {"type": "node", "id": 1207224348, "lat": 37.464525, "lon": -4.0233368}, {"type": "node", "id": 1207224352, "lat": 37.5098533, "lon": -4.0625211}, {"type": "node", "id": 1207224356, "lat": 37.5277158, "lon": -4.042439}, {"type": "node", "id": 1207224361, "lat": 37.5475761, "lon": -3.9664585}, {"type": "node", "id": 1207224380, "lat": 37.5132176, "lon": -4.0626464}, {"type": "node", "id": 1207224387, "lat": 37.5294358, "lon": -4.0355047}, {"type": "node", "id": 1207224391, "lat": 37.5418338, "lon": -3.9596387}, {"type": "node", "id": 1207224407, "lat": 37.4907301, "lon": -4.0508697}, {"type": "node", "id": 1207224411, "lat": 37.5385558, "lon": -4.0379627}, {"type": "node", "id": 1207224415, "lat": 37.5323262, "lon": -4.0342637}, {"type": "node", "id": 1207224419, "lat": 37.5436433, "lon": -3.9924061}, {"type": "node", "id": 1207224431, "lat": 37.4972309, "lon": -4.0532988}, {"type": "node", "id": 1207224433, "lat": 37.5444601, "lon": -4.0380712}, {"type": "node", "id": 1207224435, "lat": 37.5249398, "lon": -4.0481743}, {"type": "node", "id": 1207224437, "lat": 37.5462179, "lon": -3.9810323}, {"type": "node", "id": 1207224444, "lat": 37.4654661, "lon": -4.0257851}, {"type": "node", "id": 1207224448, "lat": 37.5254473, "lon": -4.0440638}, {"type": "node", "id": 1207224453, "lat": 37.5474117, "lon": -3.9730582}, {"type": "node", "id": 1207224458, "lat": 37.4720256, "lon": -4.0416928}, {"type": "node", "id": 1207224471, "lat": 37.5141313, "lon": -4.0608246}, {"type": "node", "id": 1207224473, "lat": 37.5397764, "lon": -3.9963168}, {"type": "node", "id": 1207224479, "lat": 37.4771463, "lon": -4.0493018}, {"type": "node", "id": 1207224490, "lat": 37.5196026, "lon": -4.0583256}, {"type": "node", "id": 1207224491, "lat": 37.5420447, "lon": -3.9923282}, {"type": "node", "id": 1207224493, "lat": 37.5346758, "lon": -3.9506694}, {"type": "node", "id": 1207224510, "lat": 37.5228136, "lon": -4.0537711}, {"type": "node", "id": 1207224519, "lat": 37.4628633, "lon": -4.0179108}, {"type": "node", "id": 1207224532, "lat": 37.5073835, "lon": -4.0600438}, {"type": "node", "id": 1207224533, "lat": 37.5464631, "lon": -4.0388934}, {"type": "node", "id": 1207224539, "lat": 37.5474997, "lon": -3.9704844}, {"type": "node", "id": 1207224570, "lat": 37.5115851, "lon": -4.0649213}, {"type": "node", "id": 1207224573, "lat": 37.5286713, "lon": -4.0389327}, {"type": "node", "id": 1207224576, "lat": 37.5445853, "lon": -3.9641788}, {"type": "node", "id": 1207224597, "lat": 37.4824196, "lon": -4.0491572}, {"type": "node", "id": 1207224600, "lat": 37.5312226, "lon": -4.0370229}, {"type": "node", "id": 1207224607, "lat": 37.5387078, "lon": -3.9572}, {"type": "node", "id": 1207224625, "lat": 37.4929726, "lon": -4.0514172}, {"type": "node", "id": 1207224628, "lat": 37.5414061, "lon": -4.0407559}, {"type": "node", "id": 1207224631, "lat": 37.5234443, "lon": -4.0518975}, {"type": "node", "id": 1207224635, "lat": 37.5448862, "lon": -3.988572}, {"type": "node", "id": 1207224649, "lat": 37.5029725, "lon": -4.0554618}, {"type": "node", "id": 1207224650, "lat": 37.5463133, "lon": -4.0388124}, {"type": "node", "id": 1207224653, "lat": 37.5260865, "lon": -4.0456259}, {"type": "node", "id": 1207224656, "lat": 37.5473318, "lon": -3.9778689}, {"type": "node", "id": 1207224665, "lat": 37.4708671, "lon": -4.0328018}, {"type": "node", "id": 1207224673, "lat": 37.5270565, "lon": -4.0416076}, {"type": "node", "id": 1207224686, "lat": 37.4741246, "lon": -4.0463799}, {"type": "node", "id": 1207224696, "lat": 37.5168073, "lon": -4.0616572}, {"type": "node", "id": 1207224699, "lat": 37.5411819, "lon": -3.9941548}, {"type": "node", "id": 1207224709, "lat": 37.5211938, "lon": -4.0564219}, {"type": "node", "id": 1207224721, "lat": 37.5425405, "lon": -3.9903891}, {"type": "node", "id": 1207224726, "lat": 37.5054011, "lon": -4.0592828}, {"type": "node", "id": 1207224747, "lat": 37.4645097, "lon": -4.02285}, {"type": "node", "id": 1207224750, "lat": 37.5093907, "lon": -4.0622175}, {"type": "node", "id": 1399195413, "lat": 37.5062493, "lon": -4.0603164}, {"type": "node", "id": 2429210590, "lat": 37.4712649, "lon": -4.0361031}, {"type": "node", "id": 2429210596, "lat": 37.473586, "lon": -4.0443037}, {"type": "node", "id": 2520934860, "lat": 37.5038907, "lon": -4.0566285}, {"type": "node", "id": 2520934877, "lat": 37.5054678, "lon": -4.0595058}, {"type": "node", "id": 2520934894, "lat": 37.5049026, "lon": -4.0587053}, {"type": "node", "id": 2520934908, "lat": 37.5044266, "lon": -4.0577846}, {"type": "node", "id": 2520934912, "lat": 37.5041028, "lon": -4.0570758}, {"type": "node", "id": 2520934994, "lat": 37.503768, "lon": -4.0564597}, {"type": "node", "id": 2520935022, "lat": 37.5056688, "lon": -4.0598316}, {"type": "node", "id": 2520935087, "lat": 37.4916957, "lon": -4.0508619}, {"type": "node", "id": 2520946777, "lat": 37.4916581, "lon": -4.0508021}, {"type": "node", "id": 2521064413, "lat": 37.5259406, "lon": -4.0447129}, {"type": "node", "id": 2521064428, "lat": 37.5259831, "lon": -4.0434147}, {"type": "node", "id": 2521064456, "lat": 37.52546, "lon": -4.0444366}, {"type": "node", "id": 2521064463, "lat": 37.5254175, "lon": -4.0441899}, {"type": "node", "id": 2521064465, "lat": 37.5254452, "lon": -4.0443669}, {"type": "node", "id": 2521064467, "lat": 37.5255068, "lon": -4.0445278}, {"type": "node", "id": 2521085801, "lat": 37.4713065, "lon": -4.0335013}, {"type": "node", "id": 2521085803, "lat": 37.4713793, "lon": -4.0348553}, {"type": "node", "id": 2521085805, "lat": 37.471435, "lon": -4.0343051}, {"type": "node", "id": 3217005118, "lat": 37.5651672, "lon": -4.0354136}, {"type": "node", "id": 3217005119, "lat": 37.5651978, "lon": -4.0352251}, {"type": "node", "id": 3217005120, "lat": 37.565215, "lon": -4.0358074}, {"type": "node", "id": 3217005121, "lat": 37.5653357, "lon": -4.0349231}, {"type": "node", "id": 3217005122, "lat": 37.5653376, "lon": -4.034696}, {"type": "node", "id": 3217005123, "lat": 37.5654429, "lon": -4.0362834}, {"type": "node", "id": 3217005124, "lat": 37.5654851, "lon": -4.0365734}, {"type": "node", "id": 3217005125, "lat": 37.5655674, "lon": -4.0368295}, {"type": "node", "id": 3217005126, "lat": 37.5659524, "lon": -4.0375834}, {"type": "node", "id": 3217005127, "lat": 37.5660711, "lon": -4.038185}, {"type": "node", "id": 3217005128, "lat": 37.5664944, "lon": -4.0389654}, {"type": "node", "id": 3217005130, "lat": 37.5667645, "lon": -4.0393665}, {"type": "node", "id": 3217005132, "lat": 37.5669675, "lon": -4.0394294}, {"type": "node", "id": 3217005133, "lat": 37.5671245, "lon": -4.0394801}, {"type": "node", "id": 3217005134, "lat": 37.5671492, "lon": -4.0408259}, {"type": "node", "id": 3217005136, "lat": 37.5672088, "lon": -4.0412086}, {"type": "node", "id": 3217005138, "lat": 37.5672356, "lon": -4.0396855}, {"type": "node", "id": 3217005139, "lat": 37.5672467, "lon": -4.0402005}, {"type": "node", "id": 3217005140, "lat": 37.5672657, "lon": -4.0399784}, {"type": "node", "id": 3217005141, "lat": 37.5673355, "lon": -4.0414632}, {"type": "node", "id": 3217005142, "lat": 37.5674282, "lon": -4.0416494}, {"type": "node", "id": 3217005146, "lat": 37.5675508, "lon": -4.0420775}, {"type": "node", "id": 3217005152, "lat": 37.5677385, "lon": -4.0428579}, {"type": "node", "id": 3217005156, "lat": 37.5680066, "lon": -4.0434523}, {"type": "node", "id": 3217005157, "lat": 37.5680263, "lon": -4.0437694}, {"type": "node", "id": 3217005158, "lat": 37.5680296, "lon": -4.043822}, {"type": "node", "id": 3217005160, "lat": 37.5680947, "lon": -4.0444164}, {"type": "node", "id": 3217005164, "lat": 37.5682766, "lon": -4.0458033}, {"type": "node", "id": 3217005165, "lat": 37.5683015, "lon": -4.0452959}, {"type": "node", "id": 3217005168, "lat": 37.5683379, "lon": -4.0463397}, {"type": "node", "id": 3217005169, "lat": 37.568359, "lon": -4.0460473}, {"type": "node", "id": 3217005173, "lat": 37.5685275, "lon": -4.0471733}, {"type": "node", "id": 3217005176, "lat": 37.568786, "lon": -4.0484225}, {"type": "node", "id": 3217005177, "lat": 37.56896, "lon": -4.0489608}, {"type": "node", "id": 3217005178, "lat": 37.5691538, "lon": -4.0495605}, {"type": "node", "id": 3217005185, "lat": 37.5695425, "lon": -4.0503676}, {"type": "node", "id": 3217005186, "lat": 37.570345, "lon": -4.0519864}, {"type": "node", "id": 3217005188, "lat": 37.5704057, "lon": -4.0520427}, {"type": "node", "id": 3217005191, "lat": 37.5711838, "lon": -4.0527645}, {"type": "node", "id": 3217005193, "lat": 37.5717296, "lon": -4.0530592}, {"type": "node", "id": 3217005196, "lat": 37.5722409, "lon": -4.0531341}, {"type": "node", "id": 3217005198, "lat": 37.5726986, "lon": -4.0531124}, {"type": "node", "id": 3217005211, "lat": 37.5736849, "lon": -4.0532936}, {"type": "node", "id": 3217005213, "lat": 37.5737671, "lon": -4.0533247}, {"type": "node", "id": 3217005220, "lat": 37.5745677, "lon": -4.053627}, {"type": "node", "id": 3217005226, "lat": 37.575079, "lon": -4.0539025}, {"type": "node", "id": 3217005236, "lat": 37.575578, "lon": -4.0542519}, {"type": "node", "id": 3217005250, "lat": 37.5766121, "lon": -4.0551459}, {"type": "node", "id": 3217005288, "lat": 37.5787627, "lon": -4.0575868}, {"type": "node", "id": 3217537847, "lat": 37.5335888, "lon": -3.9806257}, {"type": "node", "id": 3217537853, "lat": 37.5348661, "lon": -3.9818903}, {"type": "node", "id": 3217537860, "lat": 37.5352738, "lon": -3.9831919}, {"type": "node", "id": 3217537863, "lat": 37.5353478, "lon": -3.9868548}, {"type": "node", "id": 3217537868, "lat": 37.5358689, "lon": -3.9880231}, {"type": "node", "id": 3217537870, "lat": 37.5362405, "lon": -3.9884966}, {"type": "node", "id": 3217537875, "lat": 37.5373133, "lon": -3.9899371}, {"type": "node", "id": 3217537877, "lat": 37.5378057, "lon": -3.9913357}, {"type": "node", "id": 3217537881, "lat": 37.5384548, "lon": -3.9968083}, {"type": "node", "id": 3217537882, "lat": 37.5384358, "lon": -3.9974223}, {"type": "node", "id": 3217537884, "lat": 37.5385914, "lon": -3.9964135}, {"type": "node", "id": 3217537893, "lat": 37.5387301, "lon": -3.9962356}, {"type": "node", "id": 3217537895, "lat": 37.5389912, "lon": -3.996089}, {"type": "node", "id": 3217537897, "lat": 37.5392181, "lon": -3.9958193}, {"type": "node", "id": 3217537899, "lat": 37.5393841, "lon": -3.9938707}, {"type": "node", "id": 3217537900, "lat": 37.5393909, "lon": -3.9956521}, {"type": "node", "id": 3217537901, "lat": 37.5395208, "lon": -3.9954006}, {"type": "node", "id": 3217537904, "lat": 37.5399626, "lon": -4.003382}, {"type": "node", "id": 3217537905, "lat": 37.5400202, "lon": -3.992047}, {"type": "node", "id": 3217537907, "lat": 37.5400306, "lon": -3.9917506}, {"type": "node", "id": 3217537908, "lat": 37.5400457, "lon": -3.9921896}, {"type": "node", "id": 3217537910, "lat": 37.5401107, "lon": -3.9952744}, {"type": "node", "id": 3217537911, "lat": 37.5400693, "lon": -3.9916812}, {"type": "node", "id": 3217537912, "lat": 37.5401679, "lon": -4.0033353}, {"type": "node", "id": 3217537913, "lat": 37.5403285, "lon": -3.9933166}, {"type": "node", "id": 3217537914, "lat": 37.5403262, "lon": -4.0030965}, {"type": "node", "id": 3217537915, "lat": 37.5403972, "lon": -3.9935361}, {"type": "node", "id": 3217537917, "lat": 37.5404425, "lon": -3.9936349}, {"type": "node", "id": 3217537918, "lat": 37.5404117, "lon": -4.002544}, {"type": "node", "id": 3217537920, "lat": 37.540594, "lon": -3.9914167}, {"type": "node", "id": 3217537921, "lat": 37.5406206, "lon": -3.994169}, {"type": "node", "id": 3217537922, "lat": 37.5406475, "lon": -4.0013757}, {"type": "node", "id": 3217537923, "lat": 37.5407314, "lon": -3.9941164}, {"type": "node", "id": 3217537924, "lat": 37.5407587, "lon": -3.9941557}, {"type": "node", "id": 3217537926, "lat": 37.54082, "lon": -4.0004957}, {"type": "node", "id": 3217537927, "lat": 37.5408589, "lon": -3.9950985}, {"type": "node", "id": 3217537929, "lat": 37.5409802, "lon": -3.9950431}, {"type": "node", "id": 3217537930, "lat": 37.5409969, "lon": -3.9997915}, {"type": "node", "id": 3217537931, "lat": 37.5410192, "lon": -3.9943658}, {"type": "node", "id": 3217537932, "lat": 37.5410248, "lon": -3.9950083}, {"type": "node", "id": 3217537933, "lat": 37.5410637, "lon": -3.9949983}, {"type": "node", "id": 3217537934, "lat": 37.5410903, "lon": -3.9950116}, {"type": "node", "id": 3217537935, "lat": 37.5410514, "lon": -3.9996599}, {"type": "node", "id": 3217537937, "lat": 37.5411858, "lon": -3.9947215}, {"type": "node", "id": 3217537938, "lat": 37.5411896, "lon": -3.9944211}, {"type": "node", "id": 3217537939, "lat": 37.5411744, "lon": -3.9994941}, {"type": "node", "id": 3217537940, "lat": 37.541276, "lon": -3.9946268}, {"type": "node", "id": 3217537941, "lat": 37.5413537, "lon": -3.9945794}, {"type": "node", "id": 3217537942, "lat": 37.5413765, "lon": -3.9945134}, {"type": "node", "id": 3217537943, "lat": 37.5414326, "lon": -3.9943516}, {"type": "node", "id": 3217537944, "lat": 37.5414736, "lon": -3.9957843}, {"type": "node", "id": 3217537945, "lat": 37.5416555, "lon": -3.9992801}, {"type": "node", "id": 3217537947, "lat": 37.5416142, "lon": -3.9948132}, {"type": "node", "id": 3217537948, "lat": 37.5416693, "lon": -3.994889}, {"type": "node", "id": 3217537949, "lat": 37.5417837, "lon": -3.9991492}, {"type": "node", "id": 3217537950, "lat": 37.5417568, "lon": -3.9953442}, {"type": "node", "id": 3217537951, "lat": 37.541819, "lon": -3.9960932}, {"type": "node", "id": 3217537952, "lat": 37.5418597, "lon": -3.9949933}, {"type": "node", "id": 3217537953, "lat": 37.5419676, "lon": -3.9987798}, {"type": "node", "id": 3217537954, "lat": 37.5420092, "lon": -3.9983132}, {"type": "node", "id": 3217537955, "lat": 37.5420016, "lon": -3.9986436}, {"type": "node", "id": 3217537956, "lat": 37.5420438, "lon": -3.9965318}, {"type": "node", "id": 3217537958, "lat": 37.5422479, "lon": -3.9971876}, {"type": "node", "id": 3217537959, "lat": 37.5422484, "lon": -3.9980375}, {"type": "node", "id": 3217537961, "lat": 37.5422813, "lon": -3.9955936}, {"type": "node", "id": 3217537962, "lat": 37.5423054, "lon": -3.9973209}, {"type": "node", "id": 3217537963, "lat": 37.5423373, "lon": -3.9956086}, {"type": "node", "id": 3217537964, "lat": 37.5423473, "lon": -3.9974634}, {"type": "node", "id": 3217537966, "lat": 37.5423252, "lon": -3.9978523}, {"type": "node", "id": 3217537968, "lat": 37.5423674, "lon": -3.9975787}, {"type": "node", "id": 3217537969, "lat": 37.5423638, "lon": -3.9972289}, {"type": "node", "id": 3217537972, "lat": 37.5424698, "lon": -3.9964317}, {"type": "node", "id": 3217537978, "lat": 37.5426153, "lon": -3.9958826}, {"type": "node", "id": 3217537981, "lat": 37.5427365, "lon": -3.9959185}, {"type": "node", "id": 3217537984, "lat": 37.5429219, "lon": -3.995957}, {"type": "node", "id": 3217537988, "lat": 37.5432153, "lon": -3.996002}, {"type": "node", "id": 3217537991, "lat": 37.5434314, "lon": -4.0117006}, {"type": "node", "id": 3217537993, "lat": 37.5435911, "lon": -3.9962649}, {"type": "node", "id": 3217537995, "lat": 37.5437917, "lon": -4.0102563}, {"type": "node", "id": 3217537997, "lat": 37.5438215, "lon": -3.996296}, {"type": "node", "id": 3217538002, "lat": 37.5439206, "lon": -4.010273}, {"type": "node", "id": 3217538004, "lat": 37.5439421, "lon": -3.9962268}, {"type": "node", "id": 3217538010, "lat": 37.5441588, "lon": -3.9960677}, {"type": "node", "id": 3217538011, "lat": 37.5441769, "lon": -4.0104451}, {"type": "node", "id": 3217538013, "lat": 37.5444469, "lon": -4.0103624}, {"type": "node", "id": 3217538014, "lat": 37.5444632, "lon": -3.9959328}, {"type": "node", "id": 3217538016, "lat": 37.5446854, "lon": -3.9958325}, {"type": "node", "id": 3217538019, "lat": 37.5447903, "lon": -4.0103426}, {"type": "node", "id": 3217538025, "lat": 37.5449738, "lon": -4.0102665}, {"type": "node", "id": 3217538026, "lat": 37.5449761, "lon": -3.9958775}, {"type": "node", "id": 3217538029, "lat": 37.5451514, "lon": -4.0102266}, {"type": "node", "id": 3217538032, "lat": 37.545194, "lon": -4.010217}, {"type": "node", "id": 3217538033, "lat": 37.5452394, "lon": -3.9959363}, {"type": "node", "id": 3217538037, "lat": 37.5459323, "lon": -4.0106953}, {"type": "node", "id": 3217538038, "lat": 37.5459595, "lon": -4.0107129}, {"type": "node", "id": 3217538044, "lat": 37.5464209, "lon": -4.0108683}, {"type": "node", "id": 3217538049, "lat": 37.5468822, "lon": -4.0109245}, {"type": "node", "id": 3217538051, "lat": 37.5473252, "lon": -4.0111791}, {"type": "node", "id": 3217538053, "lat": 37.5480645, "lon": -4.0113047}, {"type": "node", "id": 3217538054, "lat": 37.5484813, "lon": -4.0116353}, {"type": "node", "id": 3217538055, "lat": 37.5489505, "lon": -4.0118701}, {"type": "node", "id": 3217538056, "lat": 37.5492729, "lon": -4.0121511}, {"type": "node", "id": 3217538057, "lat": 37.5495429, "lon": -4.0123792}, {"type": "node", "id": 3217538058, "lat": 37.5498994, "lon": -4.0123958}, {"type": "node", "id": 3217538059, "lat": 37.5502375, "lon": -4.0124685}, {"type": "node", "id": 3217538060, "lat": 37.5506569, "lon": -4.0127925}, {"type": "node", "id": 3217538161, "lat": 37.5511819, "lon": -4.0129315}, {"type": "node", "id": 3217538162, "lat": 37.5517528, "lon": -4.0129642}, {"type": "node", "id": 3217538163, "lat": 37.5524589, "lon": -4.0131232}, {"type": "node", "id": 3217538164, "lat": 37.5532652, "lon": -4.0131349}, {"type": "node", "id": 3217538165, "lat": 37.5539602, "lon": -4.0130648}, {"type": "node", "id": 3217538166, "lat": 37.5542234, "lon": -4.0131022}, {"type": "node", "id": 3217538167, "lat": 37.5548721, "lon": -4.0136937}, {"type": "node", "id": 3217538168, "lat": 37.5555134, "lon": -4.0141519}, {"type": "node", "id": 3217538169, "lat": 37.5559767, "lon": -4.0145867}, {"type": "node", "id": 3217538170, "lat": 37.5563937, "lon": -4.0151408}, {"type": "node", "id": 3217538171, "lat": 37.5565031, "lon": -4.0154681}, {"type": "node", "id": 3217538172, "lat": 37.5570331, "lon": -4.0163752}, {"type": "node", "id": 3217538173, "lat": 37.5575502, "lon": -4.0171444}, {"type": "node", "id": 3217538174, "lat": 37.5580247, "lon": -4.0181847}, {"type": "node", "id": 3217538175, "lat": 37.5584969, "lon": -4.0188067}, {"type": "node", "id": 3217538176, "lat": 37.5589231, "lon": -4.0193935}, {"type": "node", "id": 3217538177, "lat": 37.5589442, "lon": -4.0194637}, {"type": "node", "id": 3217538178, "lat": 37.5590269, "lon": -4.0197395}, {"type": "node", "id": 3217538179, "lat": 37.5594235, "lon": -4.0204479}, {"type": "node", "id": 3217538181, "lat": 37.5599091, "lon": -4.0207098}, {"type": "node", "id": 3217538183, "lat": 37.5601537, "lon": -4.0212171}, {"type": "node", "id": 3217538184, "lat": 37.5602353, "lon": -4.0215233}, {"type": "node", "id": 3217538185, "lat": 37.5602686, "lon": -4.0218413}, {"type": "node", "id": 3217538187, "lat": 37.5604799, "lon": -4.0223907}, {"type": "node", "id": 3217538190, "lat": 37.5608728, "lon": -4.0231248}, {"type": "node", "id": 3217538192, "lat": 37.5610785, "lon": -4.0238051}, {"type": "node", "id": 3217538193, "lat": 37.5612805, "lon": -4.0242306}, {"type": "node", "id": 3217538194, "lat": 37.5616827, "lon": -4.0247543}, {"type": "node", "id": 3217538195, "lat": 37.5618865, "lon": -4.0252476}, {"type": "node", "id": 3217538197, "lat": 37.5621404, "lon": -4.0256287}, {"type": "node", "id": 3217538198, "lat": 37.5624499, "lon": -4.0262178}, {"type": "node", "id": 3217538199, "lat": 37.5625481, "lon": -4.026648}, {"type": "node", "id": 3217538200, "lat": 37.5625778, "lon": -4.027195}, {"type": "node", "id": 3217538201, "lat": 37.562613, "lon": -4.028039}, {"type": "node", "id": 3217538202, "lat": 37.5626593, "lon": -4.026849}, {"type": "node", "id": 3217538203, "lat": 37.5627594, "lon": -4.0286819}, {"type": "node", "id": 3217538204, "lat": 37.5629447, "lon": -4.0291963}, {"type": "node", "id": 3217538205, "lat": 37.5632912, "lon": -4.0303301}, {"type": "node", "id": 3217538206, "lat": 37.5636693, "lon": -4.0308655}, {"type": "node", "id": 3217538207, "lat": 37.5638453, "lon": -4.031305}, {"type": "node", "id": 3217538208, "lat": 37.5641122, "lon": -4.0318404}, {"type": "node", "id": 3217538209, "lat": 37.5642901, "lon": -4.0320859}, {"type": "node", "id": 3217538210, "lat": 37.564518, "lon": -4.0322869}, {"type": "node", "id": 3217538211, "lat": 37.5646144, "lon": -4.0326049}, {"type": "node", "id": 3217538212, "lat": 37.5648016, "lon": -4.0328106}, {"type": "node", "id": 3217538213, "lat": 37.5650017, "lon": -4.0332431}, {"type": "node", "id": 3217538214, "lat": 37.5651611, "lon": -4.0338907}, {"type": "node", "id": 3217538215, "lat": 37.5651685, "lon": -4.0337481}, {"type": "node", "id": 4232155875, "lat": 37.5485914, "lon": -4.0428399}, {"type": "node", "id": 4285051103, "lat": 37.5453958, "lon": -3.9959957}, {"type": "node", "id": 4285051104, "lat": 37.5455275, "lon": -3.9960075}, {"type": "node", "id": 4285051105, "lat": 37.5456027, "lon": -3.996055}, {"type": "node", "id": 4285051106, "lat": 37.5457105, "lon": -3.9962098}, {"type": "node", "id": 4285051107, "lat": 37.545915, "lon": -3.9965256}, {"type": "node", "id": 4285051108, "lat": 37.5459648, "lon": -3.9965813}, {"type": "node", "id": 4285051110, "lat": 37.5464335, "lon": -3.9969322}, {"type": "node", "id": 4285051111, "lat": 37.5465076, "lon": -3.9970196}, {"type": "node", "id": 4285051112, "lat": 37.546559, "lon": -3.9971373}, {"type": "node", "id": 4285051113, "lat": 37.5466001, "lon": -3.9972754}, {"type": "node", "id": 4285051115, "lat": 37.5466488, "lon": -3.9976585}, {"type": "node", "id": 4285051116, "lat": 37.546653, "lon": -3.997733}, {"type": "node", "id": 4285051117, "lat": 37.5466256, "lon": -3.9978257}, {"type": "node", "id": 4285051118, "lat": 37.5464461, "lon": -3.9981666}, {"type": "node", "id": 4285051119, "lat": 37.546374, "lon": -3.9983327}, {"type": "node", "id": 4285051120, "lat": 37.5463301, "lon": -3.9984987}, {"type": "node", "id": 4285051413, "lat": 37.5462229, "lon": -3.9987221}, {"type": "node", "id": 4285051414, "lat": 37.5461925, "lon": -3.9988292}, {"type": "node", "id": 4285051415, "lat": 37.5461295, "lon": -3.9990053}, {"type": "node", "id": 4285051416, "lat": 37.5459829, "lon": -3.9992793}, {"type": "node", "id": 4285051417, "lat": 37.5459133, "lon": -3.9995151}, {"type": "node", "id": 4285051419, "lat": 37.5457794, "lon": -3.999944}, {"type": "node", "id": 4285051420, "lat": 37.5457481, "lon": -3.9999769}, {"type": "node", "id": 4285051421, "lat": 37.5457098, "lon": -3.9999901}, {"type": "node", "id": 4285051422, "lat": 37.5456889, "lon": -3.9999594}, {"type": "node", "id": 4285051423, "lat": 37.545675, "lon": -3.999887}, {"type": "node", "id": 4285051424, "lat": 37.5456559, "lon": -3.9997992}, {"type": "node", "id": 4285051425, "lat": 37.5456072, "lon": -3.9997488}, {"type": "node", "id": 5648383546, "lat": 37.5431438, "lon": -4.0130716}, {"type": "node", "id": 5648418573, "lat": 37.5428826, "lon": -4.009813}, {"type": "node", "id": 5648418574, "lat": 37.5426144, "lon": -4.0095978}, {"type": "node", "id": 5648418575, "lat": 37.5424286, "lon": -4.009602}, {"type": "node", "id": 5648418576, "lat": 37.5423153, "lon": -4.0095847}, {"type": "node", "id": 5648418577, "lat": 37.5421472, "lon": -4.0095501}, {"type": "node", "id": 5648418578, "lat": 37.5420374, "lon": -4.0094809}, {"type": "node", "id": 5648418579, "lat": 37.5418453, "lon": -4.0093424}, {"type": "node", "id": 5648418580, "lat": 37.5416875, "lon": -4.0092126}, {"type": "node", "id": 5648418581, "lat": 37.5415605, "lon": -4.0090006}, {"type": "node", "id": 5648418582, "lat": 37.5414542, "lon": -4.0087323}, {"type": "node", "id": 5648418583, "lat": 37.5413512, "lon": -4.0084986}, {"type": "node", "id": 5648418584, "lat": 37.5412106, "lon": -4.0082173}, {"type": "node", "id": 5648418585, "lat": 37.5411179, "lon": -4.0079923}, {"type": "node", "id": 5648418586, "lat": 37.5410699, "lon": -4.0077803}, {"type": "node", "id": 5648418587, "lat": 37.541063, "lon": -4.007538}, {"type": "node", "id": 5648418588, "lat": 37.5410699, "lon": -4.007261}, {"type": "node", "id": 5648418589, "lat": 37.5411055, "lon": -4.007085}, {"type": "node", "id": 5648427021, "lat": 37.5430696, "lon": -4.0133941}, {"type": "node", "id": 5648909620, "lat": 37.5426968, "lon": -4.0093882}, {"type": "node", "id": 5648918526, "lat": 37.5423781, "lon": -4.0087885}, {"type": "node", "id": 5649533296, "lat": 37.5413309, "lon": -4.008458}, {"type": "node", "id": 6942909346, "lat": 37.5446277, "lon": -4.0326586}, {"type": "node", "id": 6942909347, "lat": 37.5442291, "lon": -4.029164}, {"type": "node", "id": 6942909348, "lat": 37.5439011, "lon": -4.0255821}, {"type": "node", "id": 6942909361, "lat": 37.5435785, "lon": -4.0219068}, {"type": "node", "id": 6942909362, "lat": 37.5437241, "lon": -4.0236171}, {"type": "node", "id": 6942909364, "lat": 37.5438212, "lon": -4.0247101}, {"type": "node", "id": 6942909365, "lat": 37.5433693, "lon": -4.0194483}, {"type": "node", "id": 6942932148, "lat": 37.5460442, "lon": -4.0381005}, {"type": "node", "id": 6942932149, "lat": 37.546237, "lon": -4.0386976}, {"type": "node", "id": 6942932150, "lat": 37.5457549, "lon": -4.0379737}, {"type": "node", "id": 6942932151, "lat": 37.5473182, "lon": -4.0397439}, {"type": "node", "id": 6942932152, "lat": 37.5465951, "lon": -4.038197}, {"type": "node", "id": 6942932153, "lat": 37.5475815, "lon": -4.0403563}, {"type": "node", "id": 6942932154, "lat": 37.5460269, "lon": -4.037095}, {"type": "node", "id": 6942932155, "lat": 37.5452165, "lon": -4.0355873}, {"type": "node", "id": 6942932156, "lat": 37.5458237, "lon": -4.0379864}, {"type": "node", "id": 6943050345, "lat": 37.5435953, "lon": -4.0221043}, {"type": "node", "id": 6943050346, "lat": 37.5440347, "lon": -4.0270409}, {"type": "node", "id": 6943059409, "lat": 37.5386796, "lon": -3.9943595}, {"type": "node", "id": 7426770533, "lat": 37.5722685, "lon": -4.0531328}, {"type": "node", "id": 8300724465, "lat": 37.5407644, "lon": -4.0007178}, {"type": "node", "id": 9964442042, "lat": 37.5416458, "lon": -4.0408554}, {"type": "node", "id": 10271132108, "lat": 37.5323052, "lon": -4.0326551}, {"type": "node", "id": 10271313732, "lat": 37.5222249, "lon": -4.0560039}, {"type": "node", "id": 10285770065, "lat": 37.5419945, "lon": -4.0408894}, {"type": "node", "id": 10583725417, "lat": 37.5418176, "lon": -4.0409143}, {"type": "node", "id": 10583725418, "lat": 37.5413341, "lon": -4.0406866}, {"type": "node", "id": 10583725419, "lat": 37.5412198, "lon": -4.0404146}, {"type": "node", "id": 10839235935, "lat": 37.5848392, "lon": -4.0620607}, {"type": "node", "id": 10839236564, "lat": 37.5458649, "lon": -3.9964497}, {"type": "node", "id": 10839236565, "lat": 37.5456599, "lon": -3.9961228}, {"type": "node", "id": 11311337788, "lat": 37.4619571, "lon": -4.0165714}, {"type": "node", "id": 11311337789, "lat": 37.4627314, "lon": -4.017675}, {"type": "node", "id": 11311337790, "lat": 37.463151, "lon": -4.0186893}, {"type": "node", "id": 11311337791, "lat": 37.4630703, "lon": -4.0184163}, {"type": "node", "id": 11311337811, "lat": 37.4618931, "lon": -4.0164908, "tags": {"direction": "both", "distance": "0", "highway": "milestone", "ref": "JA-4305"}}, {"type": "node", "id": 11504225968, "lat": 37.4621349, "lon": -4.0168214}, {"type": "node", "id": 11811376780, "lat": 37.5001501, "lon": -4.0543545}, {"type": "node", "id": 11811376787, "lat": 37.5006592, "lon": -4.0545743}, {"type": "node", "id": 11811376789, "lat": 37.5004855, "lon": -4.0544993}, {"type": "node", "id": 11811376790, "lat": 37.5003194, "lon": -4.0544276}, {"type": "node", "id": 12027489642, "lat": 37.5400146, "lon": -3.991868}, {"type": "node", "id": 12027489643, "lat": 37.5389286, "lon": -3.9961337}, {"type": "node", "id": 12027489644, "lat": 37.5384819, "lon": -3.9966798}, {"type": "node", "id": 12027489645, "lat": 37.539597, "lon": -3.995355}, {"type": "node", "id": 12027489646, "lat": 37.5398714, "lon": -3.9961491}, {"type": "node", "id": 12027489647, "lat": 37.5402317, "lon": -3.9945087}, {"type": "node", "id": 12027489648, "lat": 37.5402865, "lon": -3.9944195}, {"type": "node", "id": 12027489649, "lat": 37.5419661, "lon": -3.996325}, {"type": "node", "id": 12027489650, "lat": 37.5423608, "lon": -3.9956272}, {"type": "node", "id": 12027489651, "lat": 37.542429, "lon": -3.9957292}, {"type": "node", "id": 12027489652, "lat": 37.5425302, "lon": -3.9958336}, {"type": "node", "id": 12027489653, "lat": 37.5424729, "lon": -3.9965008}, {"type": "node", "id": 12027489654, "lat": 37.5424029, "lon": -3.9970573}, {"type": "node", "id": 12027489655, "lat": 37.542408, "lon": -3.9969039}, {"type": "node", "id": 12027489656, "lat": 37.5423952, "lon": -3.9971336}, {"type": "node", "id": 12027489657, "lat": 37.5423577, "lon": -3.9976981}, {"type": "node", "id": 12027489658, "lat": 37.5421756, "lon": -3.9981494}, {"type": "node", "id": 12027489659, "lat": 37.5419947, "lon": -3.9983292}, {"type": "node", "id": 12027489660, "lat": 37.5419922, "lon": -3.9983541}, {"type": "node", "id": 12027489661, "lat": 37.54201, "lon": -3.9985749}, {"type": "node", "id": 12027489662, "lat": 37.5418528, "lon": -3.9990511}, {"type": "node", "id": 12027489663, "lat": 37.5409646, "lon": -3.9999906}, {"type": "node", "id": 12027489664, "lat": 37.5409487, "lon": -4.0000797}, {"type": "node", "id": 12027489667, "lat": 37.5405603, "lon": -4.0017033}, {"type": "node", "id": 12027489668, "lat": 37.5403814, "lon": -4.0028636}, {"type": "node", "id": 12027506769, "lat": 37.5402534, "lon": -4.0032394}, {"type": "node", "id": 12027506770, "lat": 37.5400853, "lon": -4.0033703}, {"type": "node", "id": 12027506771, "lat": 37.5423685, "lon": -3.9599262}, {"type": "node", "id": 12027506772, "lat": 37.5427129, "lon": -3.9603541}, {"type": "node", "id": 12027506773, "lat": 37.5431516, "lon": -3.9611627}, {"type": "node", "id": 12027506774, "lat": 37.5433299, "lon": -3.9617264}, {"type": "node", "id": 12027506775, "lat": 37.5434343, "lon": -3.9623736}, {"type": "node", "id": 12027506776, "lat": 37.5433833, "lon": -3.9629839}, {"type": "node", "id": 12027506777, "lat": 37.5434305, "lon": -3.963122}, {"type": "node", "id": 12027506778, "lat": 37.5460777, "lon": -3.9652499}, {"type": "node", "id": 12027506779, "lat": 37.546261, "lon": -3.9655277}, {"type": "node", "id": 12027506780, "lat": 37.5463464, "lon": -3.9655775}, {"type": "node", "id": 12027506781, "lat": 37.5469346, "lon": -3.9657654}, {"type": "node", "id": 12027506782, "lat": 37.5477075, "lon": -3.9668446}, {"type": "node", "id": 12027506783, "lat": 37.5484205, "lon": -3.9679398}, {"type": "node", "id": 12027506784, "lat": 37.5484282, "lon": -3.9681069}, {"type": "node", "id": 12027506785, "lat": 37.5483518, "lon": -3.9684184}, {"type": "node", "id": 12027506786, "lat": 37.5480958, "lon": -3.9689548}, {"type": "node", "id": 12027506787, "lat": 37.548106, "lon": -3.9692551}, {"type": "node", "id": 12027506788, "lat": 37.5480971, "lon": -3.9693611}, {"type": "node", "id": 12027506789, "lat": 37.5479927, "lon": -3.9696373}, {"type": "node", "id": 12027506790, "lat": 37.5477508, "lon": -3.9699971}, {"type": "node", "id": 12027506791, "lat": 37.5475802, "lon": -3.9703022}, {"type": "node", "id": 12027506792, "lat": 37.5471332, "lon": -3.9716271}, {"type": "node", "id": 12027506793, "lat": 37.5477075, "lon": -3.9736233}, {"type": "node", "id": 12027506794, "lat": 37.5477011, "lon": -3.9737373}, {"type": "node", "id": 12027506795, "lat": 37.5473293, "lon": -3.9724686}, {"type": "node", "id": 12027506796, "lat": 37.5473663, "lon": -3.9729054}, {"type": "node", "id": 12027506797, "lat": 37.5472529, "lon": -3.9745531}, {"type": "node", "id": 12027506798, "lat": 37.5472007, "lon": -3.9747362}, {"type": "node", "id": 12027506799, "lat": 37.5471269, "lon": -3.975422}, {"type": "node", "id": 12027506800, "lat": 37.5471141, "lon": -3.9761061}, {"type": "node", "id": 12027506801, "lat": 37.5472237, "lon": -3.9766923}, {"type": "node", "id": 12027506802, "lat": 37.547309, "lon": -3.977749}, {"type": "node", "id": 12027506803, "lat": 37.5474643, "lon": -3.9782035}, {"type": "node", "id": 12027506804, "lat": 37.5476311, "lon": -3.9793517}, {"type": "node", "id": 12027506805, "lat": 37.54757, "lon": -3.979493}, {"type": "node", "id": 12027506806, "lat": 37.5469588, "lon": -3.980394}, {"type": "node", "id": 12027506807, "lat": 37.5463031, "lon": -3.980895}, {"type": "node", "id": 12027506808, "lat": 37.5455989, "lon": -3.9828206}, {"type": "node", "id": 12027506809, "lat": 37.5456117, "lon": -3.9834308}, {"type": "node", "id": 12027506810, "lat": 37.5456766, "lon": -3.9843366}, {"type": "node", "id": 12027506811, "lat": 37.5456155, "lon": -3.9845438}, {"type": "node", "id": 12027506812, "lat": 37.5450323, "lon": -3.9853419}, {"type": "node", "id": 12027506813, "lat": 37.5446618, "lon": -3.9859763}, {"type": "node", "id": 12027506814, "lat": 37.5443918, "lon": -3.986882}, {"type": "node", "id": 12027506815, "lat": 37.5443893, "lon": -3.9870265}, {"type": "node", "id": 12027506816, "lat": 37.5448948, "lon": -3.9888059}, {"type": "node", "id": 12027506817, "lat": 37.5443536, "lon": -3.9908294}, {"type": "node", "id": 12027506818, "lat": 37.5443167, "lon": -3.991141}, {"type": "node", "id": 12027506819, "lat": 37.5440417, "lon": -3.9918942}, {"type": "node", "id": 12027506820, "lat": 37.5437806, "lon": -3.9923005}, {"type": "node", "id": 12027506821, "lat": 37.5435005, "lon": -3.9924498}, {"type": "node", "id": 12027506822, "lat": 37.5432076, "lon": -3.9923728}, {"type": "node", "id": 12027506823, "lat": 37.5429517, "lon": -3.9920371}, {"type": "node", "id": 12027506824, "lat": 37.5427874, "lon": -3.9914301}, {"type": "node", "id": 12027506825, "lat": 37.5426766, "lon": -3.9909258}, {"type": "node", "id": 12027506826, "lat": 37.5424653, "lon": -3.990346}, {"type": "node", "id": 12027506827, "lat": 37.542613, "lon": -3.9904761}, {"type": "node", "id": 12027506828, "lat": 37.5423838, "lon": -3.9903404}, {"type": "node", "id": 12027506829, "lat": 37.5421711, "lon": -3.9905412}, {"type": "node", "id": 12027506830, "lat": 37.5421628, "lon": -3.9906721}, {"type": "node", "id": 12027506831, "lat": 37.5423265, "lon": -3.9911587}, {"type": "node", "id": 12027506832, "lat": 37.5423583, "lon": -3.9914445}, {"type": "node", "id": 12027506833, "lat": 37.5422233, "lon": -3.9921929}, {"type": "node", "id": 12027506834, "lat": 37.5423074, "lon": -3.9919536}, {"type": "node", "id": 12027506835, "lat": 37.5421635, "lon": -3.9922571}, {"type": "node", "id": 12027506836, "lat": 37.5415535, "lon": -3.9925125}, {"type": "node", "id": 12027506837, "lat": 37.5415026, "lon": -3.9926072}, {"type": "node", "id": 12027506838, "lat": 37.5415179, "lon": -3.9928288}, {"type": "node", "id": 12027506839, "lat": 37.5416974, "lon": -3.9931292}, {"type": "node", "id": 12027506840, "lat": 37.541784, "lon": -3.9935242}, {"type": "node", "id": 12027506841, "lat": 37.5417089, "lon": -3.9938695}, {"type": "node", "id": 12027506842, "lat": 37.5414376, "lon": -3.9940992}, {"type": "way", "id": 104656462, "nodes": [1207224628, 10583725418, 10583725419, 1207222571, 1207222921, 1207223326, 1207223769, 1207224124, 1207224411, 1207222391, 1207222728, 1207223098, 1207223522, 1207222923, 1207223330, 1207223770, 1207224126, 1207224415, 1207222393, 1207222729, 10271132108, 1207223101, 1207223523, 1207223947, 1207224259, 1207224600, 1207222547, 1207222888, 1207223300, 1207223737, 1207224108, 1207224387, 1207222364, 1207222705, 1207223077, 1207223490, 1207223927, 1207224245, 1207224573, 1207222527, 1207222864, 1207223272, 1207223706, 1207224088, 1207224356, 1207222342, 1207223157, 1207223579, 1207223983, 1207224291, 1207224673, 1207222604, 1207222959, 1207223355, 1207223800, 2521064428, 1207224161, 1207224448, 2521064463, 1207222429, 2521064465, 2521064456, 2521064467, 1207222764, 1207223145, 2521064413, 1207223564, 1207223973, 1207224283, 1207224653, 1207222593, 1207222943, 1207223345, 1207223788, 1207224151, 1207224435, 1207222413, 1207222759, 1207223119, 1207223544, 1207223963, 1207224274, 1207224631, 1207222572, 1207223436, 1207223862, 1207224200, 1207224510, 1207222482, 1207222813, 1207223209, 10271313732, 1207223623, 1207224030, 1207224320, 1207224709, 1207222638, 1207222993, 1207223407, 1207223850, 1207224186, 1207224490, 1207222465, 1207222800, 1207223191, 1207223611, 1207224005, 1207224308, 1207224696, 1207222619, 1207222968, 1207223390, 1207223821, 1207224177, 1207224471, 1207222443, 1207222785, 1207223735, 1207224106, 1207224380, 1207222363, 1207222703, 1207223071, 1207223487, 1207223917, 1207224240, 1207224570, 1207222524, 1207222861, 1207223266, 1207223699, 1207224085, 1207224352, 1207224750, 1207222679, 1207223037, 1207223451, 1207223883, 1207224212, 1207224532, 1207222498, 1207222831, 1207223244, 1207223658, 1399195413, 1207224052, 2520935022, 1207224329, 2520934877, 1207224726, 1207222658, 2520934894, 1207223008, 2520934908, 2520934912, 1207223972, 2520934860, 2520934994, 1207224282, 1207224649, 1207222582, 1207222938, 11811376787, 11811376789, 11811376790, 11811376780, 1207223342, 1207223784, 1207224147, 1207224431, 1207222410, 1207222748, 1207223116, 1207223540, 1207223961, 1207224271, 1207224625, 1207222564, 1207222918, 1207223315, 2520935087, 2520946777, 1207223767, 1207224122, 1207224407, 1207222389, 1207222727, 1207223095, 1207223508, 1207223946, 1207224258, 1207224597, 1207222545, 1207222887, 1207223299, 1207224183, 1207224479, 1207222454, 1207222797, 1207223177, 1207223590, 1207223999, 1207224300, 1207224686, 1207222615, 1207222965, 2429210596, 1207223384, 1207223819, 1207224174, 1207224458, 1207222437, 1207222779, 1207223155, 1207223574, 2429210590, 2521085803, 2521085805, 1207223979, 2521085801, 1207224287, 1207224665, 1207222600, 1207222950, 1207223352, 1207223799, 1207224160, 1207224444, 1207222427, 1207222763, 1207223127, 1207223554, 1207224348, 1207224747, 1207222674, 1207223033, 1207223447, 1207223878, 11311337790, 11311337791, 1207224209, 1207224519, 11311337789, 1207222494, 11504225968, 11311337788, 11311337811, 1207222827], "tags": {"highway": "tertiary", "lanes": "2", "oneway": "no", "ref": "JA-4305", "surface": "asphalt"}}, {"type": "way", "id": 104656485, "nodes": [1207224473, 12027489646, 1207224178, 1207223823, 3217537910, 1207223391, 12027489647, 12027489648, 3217537921], "tags": {"highway": "tertiary", "ref": "JA-4306", "source": "PNOA"}}, {"type": "way", "id": 315571957, "nodes": [33193767, 3217537995, 3217538002, 3217538011, 3217538013, 3217538019, 3217538025, 3217538029], "tags": {"highway": "unclassified"}}, {"type": "way", "id": 315623456, "nodes": [3217537923, 1207222621, 1207224699, 12027506842, 1207224309, 12027506841, 1207224013, 12027506840, 1207223614, 12027506839, 1207223193, 12027506838, 1207222801, 12027506837, 12027506836, 1207222466, 1207224491, 12027506835, 12027506833, 1207224187, 12027506834, 12027506832, 1207223853, 12027506831, 1207223412, 12027506830, 12027506829, 1207222999, 1207222641, 12027506828, 12027506826, 1207224721, 12027506827, 1207224323, 12027506825, 1207224035, 12027506824, 1207223645, 12027506823, 1207223216, 12027506822, 1207222397, 12027506821, 1207224419, 12027506820, 1207224131, 12027506819, 1207223773, 12027506818, 12027506817, 1207223332, 1207222925, 12027506816, 1207222574, 1207224635, 1207224275, 12027506815, 12027506814, 1207223965, 12027506813, 1207223546, 12027506812, 1207223120, 12027506811, 12027506810, 1207222760, 12027506809, 12027506808, 1207222414, 1207224437, 12027506807, 1207224154, 1207223790, 12027506806, 12027506805, 12027506804, 1207223348, 1207222946, 1207222596, 12027506803, 1207224656, 12027506802, 1207224284, 12027506801, 1207223974, 12027506800, 12027506799, 1207223567, 12027506798, 12027506797, 1207223151, 1207222766, 12027506794, 12027506793, 1207222432, 1207224453, 12027506796, 1207224164, 12027506795, 1207223804, 12027506792, 1207223370, 1207222961, 1207224539, 12027506791, 12027506790, 12027506789, 1207224220, 12027506788, 12027506787, 12027506786, 1207223903, 1207223462, 12027506785, 1207223048, 12027506784, 12027506783, 1207222691, 1207222345, 12027506782, 1207224361, 1207224102, 12027506781, 1207223712, 12027506780, 12027506779, 1207223276, 12027506778, 1207222866, 1207222530, 1207224576, 1207224247, 1207223930, 12027506777, 12027506776, 1207223500, 12027506775, 1207223080, 12027506774, 12027506773, 1207222707, 12027506772, 1207222371, 12027506771, 1207224391, 1207224110, 1207223744, 1207223304, 1207222890, 1207222556, 1207224607, 1207224262, 1207223949, 1207223527, 1207223103, 1207222732, 1207224310, 1207224016, 1207223616, 1207223197, 1207222806, 1207222469, 1207224493, 1207224189, 1207223854, 1207223417, 1207223001, 1207222653, 877550507], "tags": {"highway": "tertiary", "ref": "JA-4306", "source": "PNOA"}}, {"type": "way", "id": 315623457, "nodes": [3217537921, 1207222970, 3217537923], "tags": {"highway": "tertiary", "ref": "JA-4306", "source": "PNOA"}}, {"type": "way", "id": 315623463, "nodes": [3217538029, 3217538032, 3217538037, 3217538038, 3217538044, 3217538049, 3217538051, 3217538053, 3217538054, 3217538055, 3217538056, 3217538057, 3217538058, 3217538059, 3217538060, 3217538161, 3217538162, 3217538163, 3217538164, 3217538165, 3217538166, 3217538167, 3217538168, 3217538169, 3217538170, 3217538171, 3217538172, 3217538173, 3217538174, 3217538175, 3217538176, 3217538177, 3217538178, 3217538179, 3217538181, 3217538183, 3217538184, 3217538185, 3217538187, 3217538190, 3217538192, 3217538193, 3217538194, 3217538195, 3217538197, 3217538198, 3217538199, 3217538202, 3217538200, 3217538201, 3217538203, 3217538204, 3217538205, 3217538206, 3217538207, 3217538208, 3217538209, 3217538210, 3217538211, 3217538212, 3217538213, 3217538215, 3217538214, 3217005122, 3217005121, 3217005119, 3217005118, 3217005120, 3217005123, 3217005124, 3217005125, 3217005126, 3217005127, 3217005128, 3217005130, 3217005132, 3217005133, 3217005138, 3217005140, 3217005139, 3217005134, 3217005136, 3217005141, 3217005142, 3217005146, 3217005152, 3217005156, 3217005157, 3217005158, 3217005160, 3217005165, 3217005164, 3217005169, 3217005168, 3217005173, 3217005176, 3217005177, 3217005178, 3217005185, 3217005186, 3217005188, 3217005191, 3217005193, 3217005196, 7426770533, 3217005198, 3217005211, 3217005213, 3217005220, 3217005226, 3217005236, 3217005250, 1041687637, 1041688010, 1041688085, 1041687619, 1041687907, 1041688641, 3217005288, 1041687785, 1041688479, 1041687682, 1041688362, 1041687657, 1041688154, 1041687632, 1041687962, 1041687592, 1041687849, 1041688588, 1041687706, 1041687768, 10839235935, 1041688543, 1041687630], "tags": {"highway": "unclassified"}}, {"type": "way", "id": 315623464, "nodes": [3217537904, 12027506770, 3217537912, 12027506769, 3217537914, 12027489668, 3217537918, 12027489667, 3217537922, 8300724465, 3217537926, 12027489664, 12027489663, 3217537930, 3217537935, 3217537939, 3217537945, 3217537949, 12027489662, 3217537953, 3217537955, 12027489661, 12027489660, 12027489659, 3217537954, 12027489658, 3217537959, 3217537966, 12027489657, 3217537968, 3217537964], "tags": {"highway": "unclassified"}}, {"type": "way", "id": 315623467, "nodes": [3217537984, 3217537981], "tags": {"bridge": "yes", "highway": "unclassified", "layer": "1"}}, {"type": "way", "id": 315623468, "nodes": [3217537917, 3217537899], "tags": {"highway": "residential"}}, {"type": "way", "id": 315623472, "nodes": [3217537929, 3217537927, 3217537910], "tags": {"highway": "residential"}}, {"type": "way", "id": 315623473, "nodes": [3217537910, 12027489645, 3217537901, 3217537900], "tags": {"highway": "residential"}}, {"type": "way", "id": 315623474, "nodes": [3217537981, 3217537978, 12027489652, 12027489651, 12027489650, 3217537963], "tags": {"highway": "unclassified"}}, {"type": "way", "id": 315623475, "nodes": [3217537942, 3217537938, 3217537931], "tags": {"highway": "residential"}}, {"type": "way", "id": 315623478, "nodes": [3217537997, 3217537993, 3217537988, 3217537984], "tags": {"highway": "unclassified"}}, {"type": "way", "id": 315623480, "nodes": [3217537962, 3217537969, 12027489656, 12027489654, 12027489655, 12027489653, 3217537972, 3217537961], "tags": {"highway": "residential"}}, {"type": "way", "id": 315623481, "nodes": [3217537908, 3217537905, 12027489642, 3217537907, 3217537911, 3217537920], "tags": {"highway": "residential"}}, {"type": "way", "id": 315623483, "nodes": [3217537923, 3217537917, 3217537915, 3217537913, 3217537908], "tags": {"highway": "residential"}}, {"type": "way", "id": 315623484, "nodes": [3217537941, 3217537942, 3217537943, 3217537924, 3217537923], "tags": {"highway": "residential"}}, {"type": "way", "id": 315623486, "nodes": [3217538033, 3217538026, 3217538016, 3217538014, 3217538010, 3217538004, 3217537997], "tags": {"highway": "unclassified"}}, {"type": "way", "id": 315623487, "nodes": [3217537934, 3217537937, 3217537940, 3217537941, 3217537947, 3217537948, 3217537952], "tags": {"highway": "residential"}}, {"type": "way", "id": 315623488, "nodes": [3217537932, 3217537944, 3217537951, 12027489649, 3217537956, 3217537958, 3217537962, 3217537964], "tags": {"highway": "residential"}}, {"type": "way", "id": 315623489, "nodes": [3217537882, 3217537881, 12027489644, 3217537884, 3217537893, 12027489643, 3217537895, 3217537897, 3217537900], "tags": {"highway": "residential"}}, {"type": "way", "id": 315623493, "nodes": [3217537963, 3217537961, 3217537950, 3217537934, 3217537933, 3217537932, 3217537929, 3217537921], "tags": {"highway": "residential"}}, {"type": "way", "id": 429381544, "nodes": [3217538033, 4285051103, 4285051104, 4285051105, 10839236565, 4285051106, 10839236564, 4285051107, 4285051108, 4285051110, 4285051111, 4285051112, 4285051113, 4285051115, 4285051116, 4285051117, 4285051118, 4285051119, 4285051120], "tags": {"highway": "unclassified"}}, {"type": "way", "id": 429381755, "nodes": [4285051120, 4285051413, 4285051414, 4285051415, 4285051416, 4285051417, 4285051419, 4285051420, 4285051421, 4285051422, 4285051423, 4285051424, 4285051425], "tags": {"highway": "unclassified"}}, {"type": "way", "id": 591672167, "nodes": [5648418573, 5648418574, 5648418575, 5648418576, 5648418577, 5648418578, 5648418579, 5648418580, 5648418581, 5648418582, 5648418583, 5649533296, 5648418584, 5648418585, 5648418586, 5648418587, 5648418588, 5648418589], "tags": {"cycleway:both": "no", "highway": "secondary", "lane_markings": "no", "surface": "asphalt"}}, {"type": "way", "id": 741656574, "nodes": [1207223886, 33193779, 6942932151], "tags": {"highway": "trunk", "lanes": "4", "lanes:backward": "2", "lanes:forward": "2", "turn:lanes:backward": "through|right", "turn:lanes:forward": "merge_to_right|none"}}, {"type": "way", "id": 741656575, "nodes": [33193778, 6942932152], "tags": {"hazmat": "designated", "highway": "trunk", "lanes": "3", "lanes:backward": "2", "lanes:forward": "1", "ref": "N-432", "turn:lanes:backward": "none|merge_to_left"}}, {"type": "way", "id": 741656576, "nodes": [6942932151, 6942932153], "tags": {"hazmat": "designated", "highway": "trunk", "lanes": "3", "lanes:backward": "2", "lanes:forward": "1", "ref": "N-432", "turn:lanes:backward": "through|right"}}, {"type": "way", "id": 741656577, "nodes": [6942932152, 1207223886], "tags": {"hazmat": "designated", "highway": "trunk", "lanes": "3", "lanes:backward": "2", "lanes:forward": "2", "ref": "N-432", "turn:lanes:backward": "none|merge_to_left", "turn:lanes:forward": "left|through"}}, {"type": "way", "id": 741656578, "nodes": [6942932153, 33193780, 4232155875], "tags": {"hazmat": "designated", "highway": "trunk", "lanes": "2", "lanes:backward": "1", "lanes:forward": "1", "ref": "N-432"}}, {"type": "way", "id": 741656579, "nodes": [6942932154, 33193778], "tags": {"bridge": "yes", "hazmat": "designated", "highway": "trunk", "lanes": "2", "lanes:backward": "1", "lanes:forward": "1", "layer": "1", "maxweight:signed": "no", "ref": "N-432"}}, {"type": "way", "id": 741661687, "nodes": [6942909361, 6943050345], "tags": {"hazmat": "designated", "highway": "trunk", "lanes": "3", "lanes:backward": "1", "lanes:forward": "2", "ref": "N-432", "turn:lanes:forward": "none|merge_to_left"}}, {"type": "way", "id": 741661692, "nodes": [6942909365, 6942909361], "tags": {"hazmat": "designated", "highway": "trunk", "lanes": "3", "lanes:backward": "2", "lanes:forward": "1", "ref": "N-432", "turn:lanes:backward": "none|merge_to_left"}}, {"type": "way", "id": 741662629, "nodes": [6942909362, 33193774, 6942909364], "tags": {"hazmat": "designated", "highway": "trunk", "lanes": "2", "lanes:backward": "1", "lanes:forward": "1", "ref": "N-432"}}, {"type": "way", "id": 741662630, "nodes": [6943050345, 6942909362], "tags": {"hazmat": "designated", "highway": "trunk", "lanes": "3", "lanes:backward": "1", "lanes:forward": "2", "ref": "N-432", "turn:lanes:forward": "left|through"}}, {"type": "way", "id": 741662631, "nodes": [6942909364, 6942909348], "tags": {"hazmat": "designated", "highway": "trunk", "lanes": "3", "lanes:backward": "1", "lanes:forward": "2", "ref": "N-432", "turn:lanes:forward": "merge_to_right|none"}}, {"type": "way", "id": 741662632, "nodes": [6942909348, 6943050346], "tags": {"hazmat": "designated", "highway": "trunk", "lanes": "3", "lanes:backward": "2", "lanes:forward": "1", "ref": "N-432", "turn:lanes:backward": "through|slight_right"}}, {"type": "way", "id": 741662633, "nodes": [6943050346, 6942909347, 6942909346, 33193775, 33193776, 6942932155, 33193777, 6942932154], "tags": {"hazmat": "designated", "highway": "trunk", "lanes": "2", "lanes:backward": "1", "lanes:forward": "1", "ref": "N-432"}}, {"type": "way", "id": 741664491, "nodes": [6943059409, 33193755, 3217537900, 1207224473, 33193756, 33193757, 33193758, 33193759, 33193760, 33193761, 3217537904, 33193762, 33193763, 33193764, 5648418589, 33193765, 5648918526, 33193766, 5648909620, 5648418573], "tags": {"hazmat": "designated", "highway": "trunk", "lanes": "2", "lanes:backward": "1", "lanes:forward": "1", "ref": "N-432"}}, {"type": "way", "id": 741664493, "nodes": [3217537847, 33193742, 33193743, 3217537853, 33193744, 3217537860, 33193745, 33193746, 33193747, 3217537863, 33193748, 3217537868, 3217537870, 33193749, 33193750, 3217537875, 33193752, 33193753, 3217537877, 1207223926, 33193754, 6943059409], "tags": {"hazmat": "designated", "highway": "trunk", "lanes": "3", "lanes:backward": "2", "lanes:forward": "1", "ref": "N-432"}}, {"type": "way", "id": 1087557247, "nodes": [9964442042, 1207224628], "tags": {"bridge": "yes", "highway": "tertiary", "layer": "1", "ref": "JA-4305", "source": "PNOA"}}, {"type": "way", "id": 1087557248, "nodes": [1207223886, 1207224213, 1207224533, 1207224650, 6942932149, 1207222584, 1207222941, 6942932148, 1207223343, 6942932156, 6942932150, 1207223786, 1207224149, 1207224433, 1207222412, 1207222750, 1207223118, 1207223542, 1207223962, 10285770065, 10583725417, 9964442042], "tags": {"highway": "tertiary", "ref": "JA-4305", "source": "PNOA"}}, {"type": "way", "id": 1298271790, "nodes": [33193767, 33193768, 3217537991, 33193769, 5648383546, 5648427021, 33193770, 33193771, 33193773, 6942909365], "tags": {"hazmat": "designated", "highway": "trunk", "lanes": "2", "lanes:backward": "1", "lanes:forward": "1", "ref": "N-432"}}, {"type": "way", "id": 1298271791, "nodes": [5648418573, 33193767], "tags": {"bridge": "yes", "hazmat": "designated", "highway": "trunk", "lanes": "2", "lanes:backward": "1", "lanes:forward": "1", "layer": "1", "ref": "N-432"}}]}